stmodels/__init__.py
stmodels/stmodels.py
stmodels-0.0.0.1.dist-info/LICENSE
stmodels-0.0.0.1.dist-info/METADATA
stmodels-0.0.0.1.dist-info/WHEEL
stmodels-0.0.0.1.dist-info/top_level.txt
stmodels-0.0.0.1.dist-info/RECORD
